ansys/api/mapdl/VERSION
ansys/api/mapdl/__init__.py
ansys/api/mapdl/py.typed
ansys/api/mapdl/v0/C_StreamGrpc.proto
ansys/api/mapdl/v0/C_StreamGrpc_pb2.py
ansys/api/mapdl/v0/C_StreamGrpc_pb2.pyi
ansys/api/mapdl/v0/C_StreamGrpc_pb2_grpc.py
ansys/api/mapdl/v0/C_StreamGrpc_pb2_grpc.pyi
ansys/api/mapdl/v0/ansys_kernel.proto
ansys/api/mapdl/v0/ansys_kernel_pb2.py
ansys/api/mapdl/v0/ansys_kernel_pb2.pyi
ansys/api/mapdl/v0/ansys_kernel_pb2_grpc.py
ansys/api/mapdl/v0/ansys_kernel_pb2_grpc.pyi
ansys/api/mapdl/v0/mapdl.proto
ansys/api/mapdl/v0/mapdl_db.proto
ansys/api/mapdl/v0/mapdl_db_pb2.py
ansys/api/mapdl/v0/mapdl_db_pb2.pyi
ansys/api/mapdl/v0/mapdl_db_pb2_grpc.py
ansys/api/mapdl/v0/mapdl_db_pb2_grpc.pyi
ansys/api/mapdl/v0/mapdl_pb2.py
ansys/api/mapdl/v0/mapdl_pb2.pyi
ansys/api/mapdl/v0/mapdl_pb2_grpc.py
ansys/api/mapdl/v0/mapdl_pb2_grpc.pyi
ansys_api_mapdl-0.5.1.dist-info/LICENSE
ansys_api_mapdl-0.5.1.dist-info/METADATA
ansys_api_mapdl-0.5.1.dist-info/WHEEL
ansys_api_mapdl-0.5.1.dist-info/entry_points.txt
ansys_api_mapdl-0.5.1.dist-info/top_level.txt
ansys_api_mapdl-0.5.1.dist-info/RECORD
