Metadata-Version: 2.1
Name: ansys-api-mapdl
Version: 0.5.1
Summary: Autogenerated python gRPC interface package for ansys-api-mapdl, built on 08:29:45 on 14 March 2022
Home-page: https://github.com/ansys/ansys-api-mapdl
Author: ANSYS, Inc.
Author-email: support@ansys.com
License: MIT
Platform: UNKNOWN
Requires-Python: >=3.7
License-File: LICENSE
